{"cameraMode":{"drawMode":0,"name":"Shaded","section":"Shading Mode"},"sceneLighting":true,"audioPlay":false,"sceneViewState":{"showFog":true,"showMaterialUpdate":false,"showSkybox":true,"showFlares":true,"showImageEffects":true,"showParticleSystems":true},"in2DMode":false,"pivot":{"x":10.369168281555176,"y":-1.3011586666107178,"z":8.517216682434082},"rotation":{"x":-0.3257334530353546,"y":0.1741812378168106,"z":-0.061187613755464557,"w":-0.9272619485855103},"size":31.772064208984376,"orthographic":false}